.gitignore
LICENSE
MANIFEST.in
README.md
app.yaml
requirements.txt
setup.py
airlock/VERSION
airlock/__init__.py
airlock/__init__.pyc
airlock/api.py
airlock/api.pyc
airlock/api_test.py
airlock/api_test.pyc
airlock/app.py
airlock/app.pyc
airlock/config.py
airlock/config.pyc
airlock/errors.py
airlock/errors.pyc
airlock/handlers.py
airlock/handlers.pyc
airlock/handlers_test.py
airlock/handlers_test.pyc
airlock/oauth.py
airlock/oauth.pyc
airlock/urls.py
airlock/urls.pyc
airlock/users.py
airlock/users.pyc
airlock/users_test.py
airlock/users_test.pyc
airlock.egg-info/PKG-INFO
airlock.egg-info/SOURCES.txt
airlock.egg-info/dependency_links.txt
airlock.egg-info/requires.txt
airlock.egg-info/top_level.txt
lib/__init__.py
lib/nosegae.py
lib/rednose.py
lib/six.py
lib/apiclient/__init__.py
lib/gaenv/__init__.py
lib/gaenv/__main__.py
lib/googleapiclient/__init__.py
lib/googleapiclient/channel.py
lib/googleapiclient/discovery.py
lib/googleapiclient/errors.py
lib/googleapiclient/http.py
lib/googleapiclient/mimeparse.py
lib/googleapiclient/model.py
lib/googleapiclient/sample_tools.py
lib/googleapiclient/schema.py
lib/oauth2client/__init__.py
lib/oauth2client/appengine.py
lib/oauth2client/client.py
lib/oauth2client/clientsecrets.py
lib/oauth2client/crypt.py
lib/oauth2client/django_orm.py
lib/oauth2client/file.py
lib/oauth2client/gce.py
lib/oauth2client/keyring_storage.py
lib/oauth2client/locked_file.py
lib/oauth2client/multistore_file.py
lib/oauth2client/old_run.py
lib/oauth2client/service_account.py
lib/oauth2client/tools.py
lib/oauth2client/util.py
lib/oauth2client/xsrfutil.py
lib/protorpc/__init__.py
lib/protorpc/definition.py
lib/protorpc/definition_test.py
lib/protorpc/descriptor.py
lib/protorpc/descriptor_test.py
lib/protorpc/end2end_test.py
lib/protorpc/generate.py
lib/protorpc/generate_proto.py
lib/protorpc/generate_proto_test.py
lib/protorpc/generate_python.py
lib/protorpc/generate_python_test.py
lib/protorpc/generate_test.py
lib/protorpc/google_imports.py
lib/protorpc/message_types.py
lib/protorpc/message_types_test.py
lib/protorpc/messages.py
lib/protorpc/messages_test.py
lib/protorpc/non_sdk_imports.py
