Metadata-Version: 1.1
Name: airlock
Version: 0.0.13
Summary: A lightweight wrapper providing Google OAuth2 integration, sessions, XSRF validators, and user management for App Engine apps.
Home-page: https://github.com/grow/airlock
Author: Grow SDK Authors
Author-email: hello@grow.io
License: MIT
Keywords: cloud endpoints,google app engine,oauth2
Platform: UNKNOWN
Classifier: Development Status :: 2 - Pre-Alpha
Classifier: Environment :: Web Environment
Classifier: Intended Audience :: Developers
Classifier: License :: OSI Approved :: MIT License
Classifier: Natural Language :: English
Classifier: Operating System :: OS Independent
Classifier: Programming Language :: Python :: 2.7
Classifier: Programming Language :: Python
Classifier: Topic :: Internet :: WWW/HTTP :: Dynamic Content
Classifier: Topic :: Internet :: WWW/HTTP
Classifier: Topic :: Software Development :: Libraries :: Python Modules
